<?xml version="1.0" encoding="utf-8" ?>
<dwsync>
<file name="animated.less" server="204.93.193.167/public_html/demo/habita/" local="131400494320000000" remote="132303385200000000" Dst="0" />
<file name="bordered-pulled.less" server="204.93.193.167/public_html/demo/habita/" local="131400494320000000" remote="132303385200000000" Dst="0" />
<file name="core.less" server="204.93.193.167/public_html/demo/habita/" local="131400494320000000" remote="132303385200000000" Dst="0" />
<file name="fixed-width.less" server="204.93.193.167/public_html/demo/habita/" local="131400494320000000" remote="132303385200000000" Dst="0" />
<file name="font-awesome.css" server="204.93.193.167/public_html/demo/habita/" local="132303406789861244" remote="132303385200000000" Dst="0" />
<file name="font-awesome.less" server="204.93.193.167/public_html/demo/habita/" local="131400494320000000" remote="132303385200000000" Dst="0" />
<file name="icons.less" server="204.93.193.167/public_html/demo/habita/" local="131400494320000000" remote="132303385200000000" Dst="0" />
<file name="larger.less" server="204.93.193.167/public_html/demo/habita/" local="131400494320000000" remote="132303385200000000" Dst="0" />
<file name="list.less" server="204.93.193.167/public_html/demo/habita/" local="131400494320000000" remote="132303385200000000" Dst="0" />
<file name="mixins.css" server="204.93.193.167/public_html/demo/habita/" local="132303406781731234" remote="132303385200000000" Dst="0" />
<file name="mixins.less" server="204.93.193.167/public_html/demo/habita/" local="131400494320000000" remote="132303385200000000" Dst="0" />
<file name="path.less" server="204.93.193.167/public_html/demo/habita/" local="131400494320000000" remote="132303385200000000" Dst="0" />
<file name="stacked.less" server="204.93.193.167/public_html/demo/habita/" local="131400494320000000" remote="132303385200000000" Dst="0" />
<file name="rotated-flipped.less" server="204.93.193.167/public_html/demo/habita/" local="131400494320000000" remote="132303385200000000" Dst="0" />
<file name="screen-reader.less" server="204.93.193.167/public_html/demo/habita/" local="131400494320000000" remote="132303385200000000" Dst="0" />
<file name="variables.less" server="204.93.193.167/public_html/demo/habita/" local="131400494320000000" remote="132303385200000000" Dst="0" />
<file name="variables.css" server="204.93.193.167/public_html/demo/habita/" local="132303406781761232" remote="132303385200000000" Dst="0" />
<file name="animated.less" server="198.54.115.14/public_html/" local="131400494320000000" remote="132351018000000000" Dst="0" />
<file name="bordered-pulled.less" server="198.54.115.14/public_html/" local="131400494320000000" remote="132351018000000000" Dst="0" />
<file name="core.less" server="198.54.115.14/public_html/" local="131400494320000000" remote="132351018000000000" Dst="0" />
<file name="fixed-width.less" server="198.54.115.14/public_html/" local="131400494320000000" remote="132351018000000000" Dst="0" />
<file name="font-awesome.css" server="198.54.115.14/public_html/" local="132320972570603082" remote="132351018000000000" Dst="0" />
<file name="font-awesome.less" server="198.54.115.14/public_html/" local="131400494320000000" remote="132351018000000000" Dst="0" />
<file name="icons.less" server="198.54.115.14/public_html/" local="131400494320000000" remote="132351018000000000" Dst="0" />
<file name="larger.less" server="198.54.115.14/public_html/" local="131400494320000000" remote="132351018000000000" Dst="0" />
<file name="list.less" server="198.54.115.14/public_html/" local="131400494320000000" remote="132351018000000000" Dst="0" />
<file name="mixins.css" server="198.54.115.14/public_html/" local="132320972565060951" remote="132351018000000000" Dst="0" />
<file name="mixins.less" server="198.54.115.14/public_html/" local="131400494320000000" remote="132351018000000000" Dst="0" />
<file name="path.less" server="198.54.115.14/public_html/" local="131400494320000000" remote="132351018000000000" Dst="0" />
<file name="screen-reader.less" server="198.54.115.14/public_html/" local="131400494320000000" remote="132351018000000000" Dst="0" />
<file name="rotated-flipped.less" server="198.54.115.14/public_html/" local="131400494320000000" remote="132351018000000000" Dst="0" />
<file name="stacked.less" server="198.54.115.14/public_html/" local="131400494320000000" remote="132351018000000000" Dst="0" />
<file name="variables.css" server="198.54.115.14/public_html/" local="132320972565060951" remote="132351018000000000" Dst="0" />
<file name="variables.less" server="198.54.115.14/public_html/" local="131400494320000000" remote="132351018000000000" Dst="0" />
</dwsync>